probplanparse/__init__.py
probplanparse-0.1.2.dist-info/METADATA
probplanparse-0.1.2.dist-info/WHEEL
probplanparse-0.1.2.dist-info/top_level.txt
probplanparse-0.1.2.dist-info/RECORD
