Metadata-Version: 2.1
Name: probplanparse
Version: 0.1.2
Summary: Parse report from prob plan in ext planner
Home-page: UNKNOWN
Author: Tomo Bessho
Author-email: tomobessho018@gmail.com
License: UNKNOWN
Platform: UNKNOWN
Requires-Dist: pandas
